<?xml version="1.0" encoding="UTF-8"?>
<objects serializationModel="Studio.01.10.00">
    <object class="AudioFile" id="{d7ae62c8-fd61-4fa3-a673-2a333348c505}">
        <property name="assetPath">
            <value>enemy_weapon_fire_rapid_pewpew-005.wav</value>
        </property>
        <property name="frequencyInKHz">
            <value>48</value>
        </property>
        <property name="channelCount">
            <value>2</value>
        </property>
        <property name="length">
            <value>0.41583333333333333</value>
        </property>
        <relationship name="masterAssetFolder">
            <destination>{aa44b317-1909-4a99-94e7-0afeeb3ea2da}</destination>
        </relationship>
    </object>
</objects>
