<?xml version="1.0" encoding="UTF-8"?>
<objects serializationModel="Studio.01.10.00">
    <object class="AudioFile" id="{e356a646-0118-4f4c-86d8-12a1ed5c518f}">
        <property name="assetPath">
            <value>ammo_collect-005.wav</value>
        </property>
        <property name="frequencyInKHz">
            <value>48</value>
        </property>
        <property name="channelCount">
            <value>2</value>
        </property>
        <property name="length">
            <value>0.42852083333333335</value>
        </property>
        <relationship name="masterAssetFolder">
            <destination>{aa44b317-1909-4a99-94e7-0afeeb3ea2da}</destination>
        </relationship>
    </object>
</objects>
